{
  "block": 11632980,
  "blockTime": "2021-10-09T20:59:59.000Z",
  "rates": [
    {
      "symbol": "WBNB",
      "vaultSymbol": "ibWBNB",
      "vaultAddr": "0xd7D069493685A581d27824Fc46EdA46B7EfC0063",
      "interestModelAddr": "0xADcfBf2e8470493060FbE0A0aFAC66d2cB028e9c",
      "decimals": 18,
      "supply": "682058.01263626077551488",
      "debt": "313304.390951968394802093",
      "supplyRate": "0.056971033331182966",
      "borrowRate": "0.15311717631216",
      "utilization": "0.459351528971850908"
    },
    {
      "symbol": "BUSD",
      "vaultSymbol": "ibBUSD",
      "vaultAddr": "0x7C9e73d4C71dae564d41F78d56439bB4ba87592f",
      "interestModelAddr": "0xADcfBf2e8470493060FbE0A0aFAC66d2cB028e9c",
      "decimals": 18,
      "supply": "212473245.039555842042580637",
      "debt": "128532572.185186049138429263",
      "supplyRate": "0.097999523128908139",
      "borrowRate": "0.199999999976256",
      "utilization": "0.604935328028041002"
    },
    {
      "symbol": "ETH",
      "vaultSymbol": "ibETH",
      "vaultAddr": "0xbfF4a34A4644a113E8200D7F1D79b3555f723AfE",
      "interestModelAddr": "0xADcfBf2e8470493060FbE0A0aFAC66d2cB028e9c",
      "decimals": 18,
      "supply": "58616.759097927948842167",
      "debt": "13303.327938885001148735",
      "supplyRate": "0.013907233691286553",
      "borrowRate": "0.075651447011328",
      "utilization": "0.22695434110677849"
    },
    {
      "symbol": "ALPACA",
      "vaultSymbol": "ibALPACA",
      "vaultAddr": "0xf1bE8ecC990cBcb90e166b71E368299f0116d421",
      "interestModelAddr": "0xADcfBf2e8470493060FbE0A0aFAC66d2cB028e9c",
      "decimals": 18,
      "supply": "96038686.288733675812419484",
      "debt": "4033849.903020998643400133",
      "supplyRate": "0.000476333154145503",
      "borrowRate": "0.014000781185424",
      "utilization": "0.042002343627374364"
    },
    {
      "symbol": "USDT",
      "vaultSymbol": "ibUSDT",
      "vaultAddr": "0x158Da805682BdC8ee32d52833aD41E74bb951E59",
      "interestModelAddr": "0xADcfBf2e8470493060FbE0A0aFAC66d2cB028e9c",
      "decimals": 18,
      "supply": "122427145.622632934894650952",
      "debt": "66234770.003297948200580193",
      "supplyRate": "0.079027888992972527",
      "borrowRate": "0.180337918959792",
      "utilization": "0.541013756928211998"
    },
    {
      "symbol": "BTCB",
      "vaultSymbol": "ibBTCB",
      "vaultAddr": "0x08FC9Ba2cAc74742177e0afC3dC8Aed6961c24e7",
      "interestModelAddr": "0xADcfBf2e8470493060FbE0A0aFAC66d2cB028e9c",
      "decimals": 18,
      "supply": "3117.342564663108763682",
      "debt": "424.784719546595438068",
      "supplyRate": "0.005013401385783577",
      "borrowRate": "0.04542167040192",
      "utilization": "0.136265011218778878"
    },
    {
      "symbol": "TUSD",
      "vaultSymbol": "ibTUSD",
      "vaultAddr": "0x3282d2a151ca00BfE7ed17Aa16E42880248CD3Cd",
      "interestModelAddr": "0xADcfBf2e8470493060FbE0A0aFAC66d2cB028e9c",
      "decimals": 18,
      "supply": "61531072.837750425415662973",
      "debt": "12617879.581307094041677456",
      "supplyRate": "0.011353964870120841",
      "borrowRate": "0.068355054871056",
      "utilization": "0.205065164629565776"
    }
  ]
}