{
  "block": 10083321,
  "blockTime": "2021-08-16T15:59:59.000Z",
  "rates": [
    {
      "symbol": "WBNB",
      "vaultSymbol": "ibWBNB",
      "vaultAddr": "0xd7D069493685A581d27824Fc46EdA46B7EfC0063",
      "interestModelAddr": "0xADcfBf2e8470493060FbE0A0aFAC66d2cB028e9c",
      "decimals": 18,
      "supply": "735020.490876186423368929",
      "debt": "421243.86059254303281264",
      "supplyRate": "0.088681297712907504",
      "borrowRate": "0.191034973742544",
      "utilization": "0.573104921320487652"
    },
    {
      "symbol": "BUSD",
      "vaultSymbol": "ibBUSD",
      "vaultAddr": "0x7C9e73d4C71dae564d41F78d56439bB4ba87592f",
      "interestModelAddr": "0xADcfBf2e8470493060FbE0A0aFAC66d2cB028e9c",
      "decimals": 18,
      "supply": "233041614.969039031606573844",
      "debt": "140543404.861142081323324691",
      "supplyRate": "0.09769942414717159",
      "borrowRate": "0.199999999976256",
      "utilization": "0.603082865177595473"
    },
    {
      "symbol": "ETH",
      "vaultSymbol": "ibETH",
      "vaultAddr": "0xbfF4a34A4644a113E8200D7F1D79b3555f723AfE",
      "interestModelAddr": "0xADcfBf2e8470493060FbE0A0aFAC66d2cB028e9c",
      "decimals": 18,
      "supply": "67061.343363392529625578",
      "debt": "16098.287037051511278113",
      "supplyRate": "0.01555888961489824",
      "borrowRate": "0.0800177182272",
      "utilization": "0.24005315476336327"
    },
    {
      "symbol": "ALPACA",
      "vaultSymbol": "ibALPACA",
      "vaultAddr": "0xf1bE8ecC990cBcb90e166b71E368299f0116d421",
      "interestModelAddr": "0xADcfBf2e8470493060FbE0A0aFAC66d2cB028e9c",
      "decimals": 18,
      "supply": "70658288.54544045021743663",
      "debt": "7450448.325183589177098822",
      "supplyRate": "0.003001942364011643",
      "borrowRate": "0.035147791211328",
      "utilization": "0.105443373715345437"
    },
    {
      "symbol": "USDT",
      "vaultSymbol": "ibUSDT",
      "vaultAddr": "0x158Da805682BdC8ee32d52833aD41E74bb951E59",
      "interestModelAddr": "0xADcfBf2e8470493060FbE0A0aFAC66d2cB028e9c",
      "decimals": 18,
      "supply": "169256642.334001772313888959",
      "debt": "82643158.37899107445544355",
      "supplyRate": "0.064370389092285065",
      "borrowRate": "0.162757095241824",
      "utilization": "0.488271285778596503"
    },
    {
      "symbol": "BTCB",
      "vaultSymbol": "ibBTCB",
      "vaultAddr": "0x08FC9Ba2cAc74742177e0afC3dC8Aed6961c24e7",
      "interestModelAddr": "0xADcfBf2e8470493060FbE0A0aFAC66d2cB028e9c",
      "decimals": 18,
      "supply": "3671.149862266431818635",
      "debt": "722.202893515041553814",
      "supplyRate": "0.010449078340655214",
      "borrowRate": "0.06557463104976",
      "utilization": "0.196723893224337146"
    },
    {
      "symbol": "TUSD",
      "vaultSymbol": "ibTUSD",
      "vaultAddr": "0x3282d2a151ca00BfE7ed17Aa16E42880248CD3Cd",
      "interestModelAddr": "0xADcfBf2e8470493060FbE0A0aFAC66d2cB028e9c",
      "decimals": 18,
      "supply": "45494416.11237873656530086",
      "debt": "14021414.798107307240173861",
      "supplyRate": "0.025646685587090849",
      "borrowRate": "0.102733595277696",
      "utilization": "0.308200785860666775"
    }
  ]
}