{
  "block": 14516208,
  "blockTime": "2022-01-20T01:00:00.000Z",
  "rates": [
    {
      "symbol": "WBNB",
      "vaultSymbol": "ibWBNB",
      "vaultAddr": "0xd7D069493685A581d27824Fc46EdA46B7EfC0063",
      "interestModelAddr": "0xADcfBf2e8470493060FbE0A0aFAC66d2cB028e9c",
      "decimals": 18,
      "supply": "161060.277699308095401465",
      "debt": "145383.824585243286556363",
      "supplyRate": "0.171583730683530264",
      "borrowRate": "0.234673170824016",
      "utilization": "0.902667166988672379"
    },
    {
      "symbol": "BUSD",
      "vaultSymbol": "ibBUSD",
      "vaultAddr": "0x7C9e73d4C71dae564d41F78d56439bB4ba87592f",
      "interestModelAddr": "0xADcfBf2e8470493060FbE0A0aFAC66d2cB028e9c",
      "decimals": 18,
      "supply": "161974508.260244392907812573",
      "debt": "80471417.921607994752436122",
      "supplyRate": "0.066642876050567919",
      "borrowRate": "0.165605108216688",
      "utilization": "0.496815324744277612"
    },
    {
      "symbol": "ETH",
      "vaultSymbol": "ibETH",
      "vaultAddr": "0xbfF4a34A4644a113E8200D7F1D79b3555f723AfE",
      "interestModelAddr": "0xADcfBf2e8470493060FbE0A0aFAC66d2cB028e9c",
      "decimals": 18,
      "supply": "14382.842103590346754338",
      "debt": "3537.143869893297176555",
      "supplyRate": "0.016329759476064088",
      "borrowRate": "0.081976006412496",
      "utilization": "0.24592801926194617"
    },
    {
      "symbol": "ALPACA",
      "vaultSymbol": "ibALPACA",
      "vaultAddr": "0xf1bE8ecC990cBcb90e166b71E368299f0116d421",
      "interestModelAddr": "0xADcfBf2e8470493060FbE0A0aFAC66d2cB028e9c",
      "decimals": 18,
      "supply": "33974403.658890644880182608",
      "debt": "2710732.563084965610334608",
      "supplyRate": "0.001718831977847827",
      "borrowRate": "0.02659583167344",
      "utilization": "0.079787495030118161"
    },
    {
      "symbol": "USDT",
      "vaultSymbol": "ibUSDT",
      "vaultAddr": "0x158Da805682BdC8ee32d52833aD41E74bb951E59",
      "interestModelAddr": "0xADcfBf2e8470493060FbE0A0aFAC66d2cB028e9c",
      "decimals": 18,
      "supply": "86111596.314777791460299424",
      "debt": "40341699.960740290908187574",
      "supplyRate": "0.059258257099343448",
      "borrowRate": "0.156160539291312",
      "utilization": "0.468481617891191819"
    },
    {
      "symbol": "BTCB",
      "vaultSymbol": "ibBTCB",
      "vaultAddr": "0x08FC9Ba2cAc74742177e0afC3dC8Aed6961c24e7",
      "interestModelAddr": "0xADcfBf2e8470493060FbE0A0aFAC66d2cB028e9c",
      "decimals": 18,
      "supply": "1300.141873664177646219",
      "debt": "240.663013949051619398",
      "supplyRate": "0.009251261882463706",
      "borrowRate": "0.061701731376912",
      "utilization": "0.185105194151460797"
    },
    {
      "symbol": "TUSD",
      "vaultSymbol": "ibTUSD",
      "vaultAddr": "0x3282d2a151ca00BfE7ed17Aa16E42880248CD3Cd",
      "interestModelAddr": "0xADcfBf2e8470493060FbE0A0aFAC66d2cB028e9c",
      "decimals": 18,
      "supply": "59187370.28733288073768353",
      "debt": "6613705.498370855134539556",
      "supplyRate": "0.003371284310100015",
      "borrowRate": "0.037247279061456",
      "utilization": "0.111741837257910786"
    },
    {
      "symbol": "USDC",
      "vaultSymbol": "ibUSDC",
      "vaultAddr": "0x800933D685E7Dc753758cEb77C8bd34aBF1E26d7",
      "interestModelAddr": "0xADcfBf2e8470493060FbE0A0aFAC66d2cB028e9c",
      "decimals": 18,
      "supply": "5814588.809404507724255102",
      "debt": "2916560.477426798734845241",
      "supplyRate": "0.067930955068528155",
      "borrowRate": "0.16719786344592",
      "utilization": "0.501593590368687453"
    }
  ]
}