{
  "block": 10840390,
  "blockTime": "2021-09-12T05:00:00.000Z",
  "rates": [
    {
      "symbol": "WBNB",
      "vaultSymbol": "ibWBNB",
      "vaultAddr": "0xd7D069493685A581d27824Fc46EdA46B7EfC0063",
      "interestModelAddr": "0xADcfBf2e8470493060FbE0A0aFAC66d2cB028e9c",
      "decimals": 18,
      "supply": "702167.276936510733504887",
      "debt": "350070.980566398722687672",
      "supplyRate": "0.067111170550817054",
      "borrowRate": "0.166185937003248",
      "utilization": "0.49855781103005145"
    },
    {
      "symbol": "BUSD",
      "vaultSymbol": "ibBUSD",
      "vaultAddr": "0x7C9e73d4C71dae564d41F78d56439bB4ba87592f",
      "interestModelAddr": "0xADcfBf2e8470493060FbE0A0aFAC66d2cB028e9c",
      "decimals": 18,
      "supply": "217020718.800078316897639802",
      "debt": "151793571.130599099744507843",
      "supplyRate": "0.113309727551362201",
      "borrowRate": "0.199999999976256",
      "utilization": "0.699442762745767486"
    },
    {
      "symbol": "ETH",
      "vaultSymbol": "ibETH",
      "vaultAddr": "0xbfF4a34A4644a113E8200D7F1D79b3555f723AfE",
      "interestModelAddr": "0xADcfBf2e8470493060FbE0A0aFAC66d2cB028e9c",
      "decimals": 18,
      "supply": "48425.233347369850665227",
      "debt": "13594.969533009495668325",
      "supplyRate": "0.021280253494658749",
      "borrowRate": "0.093580478532288",
      "utilization": "0.280741435678551821"
    },
    {
      "symbol": "ALPACA",
      "vaultSymbol": "ibALPACA",
      "vaultAddr": "0xf1bE8ecC990cBcb90e166b71E368299f0116d421",
      "interestModelAddr": "0xADcfBf2e8470493060FbE0A0aFAC66d2cB028e9c",
      "decimals": 18,
      "supply": "91807176.029036359076225908",
      "debt": "2065534.834344151121783016",
      "supplyRate": "0.00013667074236945",
      "borrowRate": "0.007499540240496",
      "utilization": "0.022498620736257839"
    },
    {
      "symbol": "USDT",
      "vaultSymbol": "ibUSDT",
      "vaultAddr": "0x158Da805682BdC8ee32d52833aD41E74bb951E59",
      "interestModelAddr": "0xADcfBf2e8470493060FbE0A0aFAC66d2cB028e9c",
      "decimals": 18,
      "supply": "136205889.809268102379184028",
      "debt": "63829664.190096309263841524",
      "supplyRate": "0.059294868178625925",
      "borrowRate": "0.156208771585008",
      "utilization": "0.46862631476126543"
    },
    {
      "symbol": "BTCB",
      "vaultSymbol": "ibBTCB",
      "vaultAddr": "0x08FC9Ba2cAc74742177e0afC3dC8Aed6961c24e7",
      "interestModelAddr": "0xADcfBf2e8470493060FbE0A0aFAC66d2cB028e9c",
      "decimals": 18,
      "supply": "2661.268462138499041296",
      "debt": "477.094203766070624369",
      "supplyRate": "0.008677500952418896",
      "borrowRate": "0.059757744641472",
      "utilization": "0.179273234006123149"
    },
    {
      "symbol": "TUSD",
      "vaultSymbol": "ibTUSD",
      "vaultAddr": "0x3282d2a151ca00BfE7ed17Aa16E42880248CD3Cd",
      "interestModelAddr": "0xADcfBf2e8470493060FbE0A0aFAC66d2cB028e9c",
      "decimals": 18,
      "supply": "46665296.724444350902955978",
      "debt": "11108520.647762887056360385",
      "supplyRate": "0.015299884555771077",
      "borrowRate": "0.079348905388224",
      "utilization": "0.238046716243078972"
    }
  ]
}