{
  "block": 13211801,
  "blockTime": "2021-12-05T09:00:01.000Z",
  "rates": [
    {
      "symbol": "WBNB",
      "vaultSymbol": "ibWBNB",
      "vaultAddr": "0xd7D069493685A581d27824Fc46EdA46B7EfC0063",
      "interestModelAddr": "0xADcfBf2e8470493060FbE0A0aFAC66d2cB028e9c",
      "decimals": 18,
      "supply": "346635.32104039523329637",
      "debt": "192813.742438391425731874",
      "supplyRate": "0.083539929571276286",
      "borrowRate": "0.185414594457456",
      "utilization": "0.556243783408101762"
    },
    {
      "symbol": "BUSD",
      "vaultSymbol": "ibBUSD",
      "vaultAddr": "0x7C9e73d4C71dae564d41F78d56439bB4ba87592f",
      "interestModelAddr": "0xADcfBf2e8470493060FbE0A0aFAC66d2cB028e9c",
      "decimals": 18,
      "supply": "174523043.930607974137898847",
      "debt": "88366550.490897924525226232",
      "supplyRate": "0.069220384928647035",
      "borrowRate": "0.168777235175184",
      "utilization": "0.506331705548485089"
    },
    {
      "symbol": "ETH",
      "vaultSymbol": "ibETH",
      "vaultAddr": "0xbfF4a34A4644a113E8200D7F1D79b3555f723AfE",
      "interestModelAddr": "0xADcfBf2e8470493060FbE0A0aFAC66d2cB028e9c",
      "decimals": 18,
      "supply": "22143.67213592925322424",
      "debt": "3815.023581648935433909",
      "supplyRate": "0.008014177046191756",
      "borrowRate": "0.057428348786784",
      "utilization": "0.172285046411017907"
    },
    {
      "symbol": "ALPACA",
      "vaultSymbol": "ibALPACA",
      "vaultAddr": "0xf1bE8ecC990cBcb90e166b71E368299f0116d421",
      "interestModelAddr": "0xADcfBf2e8470493060FbE0A0aFAC66d2cB028e9c",
      "decimals": 18,
      "supply": "91095625.126094738589088125",
      "debt": "2406780.308932527197187033",
      "supplyRate": "0.000188469735662824",
      "borrowRate": "0.008806790664",
      "utilization": "0.026420372060689602"
    },
    {
      "symbol": "USDT",
      "vaultSymbol": "ibUSDT",
      "vaultAddr": "0x158Da805682BdC8ee32d52833aD41E74bb951E59",
      "interestModelAddr": "0xADcfBf2e8470493060FbE0A0aFAC66d2cB028e9c",
      "decimals": 18,
      "supply": "120877293.364132194526336874",
      "debt": "64307144.330952957980378047",
      "supplyRate": "0.076417488304161481",
      "borrowRate": "0.17733450326256",
      "utilization": "0.53200350985055028"
    },
    {
      "symbol": "BTCB",
      "vaultSymbol": "ibBTCB",
      "vaultAddr": "0x08FC9Ba2cAc74742177e0afC3dC8Aed6961c24e7",
      "interestModelAddr": "0xADcfBf2e8470493060FbE0A0aFAC66d2cB028e9c",
      "decimals": 18,
      "supply": "1946.935682236198090966",
      "debt": "331.743352554803790076",
      "supplyRate": "0.00783907849425784",
      "borrowRate": "0.05679751954608",
      "utilization": "0.170392558717590647"
    },
    {
      "symbol": "TUSD",
      "vaultSymbol": "ibTUSD",
      "vaultAddr": "0x3282d2a151ca00BfE7ed17Aa16E42880248CD3Cd",
      "interestModelAddr": "0xADcfBf2e8470493060FbE0A0aFAC66d2cB028e9c",
      "decimals": 18,
      "supply": "59259000.780022737251805083",
      "debt": "6277561.752600840436247124",
      "supplyRate": "0.003029961447991926",
      "borrowRate": "0.035311438863216",
      "utilization": "0.105934316643373408"
    }
  ]
}