{
  "block": 14680247,
  "blockTime": "2022-01-25T18:00:00.000Z",
  "rates": [
    {
      "symbol": "WBNB",
      "vaultSymbol": "ibWBNB",
      "vaultAddr": "0xd7D069493685A581d27824Fc46EdA46B7EfC0063",
      "interestModelAddr": "0xADcfBf2e8470493060FbE0A0aFAC66d2cB028e9c",
      "decimals": 18,
      "supply": "372264.201297904784459007",
      "debt": "154634.771477541610666287",
      "supplyRate": "0.046588156856765747",
      "borrowRate": "0.138463283967552",
      "utilization": "0.415389851987929901"
    },
    {
      "symbol": "BUSD",
      "vaultSymbol": "ibBUSD",
      "vaultAddr": "0x7C9e73d4C71dae564d41F78d56439bB4ba87592f",
      "interestModelAddr": "0xADcfBf2e8470493060FbE0A0aFAC66d2cB028e9c",
      "decimals": 18,
      "supply": "154489772.6433264774726739",
      "debt": "53043458.501161028133136054",
      "supplyRate": "0.031829364065344166",
      "borrowRate": "0.114448694739408",
      "utilization": "0.34334608429791327"
    },
    {
      "symbol": "ETH",
      "vaultSymbol": "ibETH",
      "vaultAddr": "0xbfF4a34A4644a113E8200D7F1D79b3555f723AfE",
      "interestModelAddr": "0xADcfBf2e8470493060FbE0A0aFAC66d2cB028e9c",
      "decimals": 18,
      "supply": "11389.822870753227439233",
      "debt": "3460.281048562843203123",
      "supplyRate": "0.024920260173506068",
      "borrowRate": "0.10126821366864",
      "utilization": "0.303804641022833501"
    },
    {
      "symbol": "ALPACA",
      "vaultSymbol": "ibALPACA",
      "vaultAddr": "0xf1bE8ecC990cBcb90e166b71E368299f0116d421",
      "interestModelAddr": "0xADcfBf2e8470493060FbE0A0aFAC66d2cB028e9c",
      "decimals": 18,
      "supply": "31476423.050917181147820865",
      "debt": "3129867.180459782324173263",
      "supplyRate": "0.00266959163439407",
      "borrowRate": "0.03314509585992",
      "utilization": "0.09943528765631399"
    },
    {
      "symbol": "USDT",
      "vaultSymbol": "ibUSDT",
      "vaultAddr": "0x158Da805682BdC8ee32d52833aD41E74bb951E59",
      "interestModelAddr": "0xADcfBf2e8470493060FbE0A0aFAC66d2cB028e9c",
      "decimals": 18,
      "supply": "103667877.760680948553579604",
      "debt": "36520784.246593089269016789",
      "supplyRate": "0.03350854250862049",
      "borrowRate": "0.117428802525936",
      "utilization": "0.352286407665274466"
    },
    {
      "symbol": "BTCB",
      "vaultSymbol": "ibBTCB",
      "vaultAddr": "0x08FC9Ba2cAc74742177e0afC3dC8Aed6961c24e7",
      "interestModelAddr": "0xADcfBf2e8470493060FbE0A0aFAC66d2cB028e9c",
      "decimals": 18,
      "supply": "1841.655655127714620037",
      "debt": "212.270779587762308318",
      "supplyRate": "0.003586966594478168",
      "borrowRate": "0.038420280322992",
      "utilization": "0.11526084097031799"
    },
    {
      "symbol": "TUSD",
      "vaultSymbol": "ibTUSD",
      "vaultAddr": "0x3282d2a151ca00BfE7ed17Aa16E42880248CD3Cd",
      "interestModelAddr": "0xADcfBf2e8470493060FbE0A0aFAC66d2cB028e9c",
      "decimals": 18,
      "supply": "59146251.568543235006538351",
      "debt": "4985252.347155173460782283",
      "supplyRate": "0.00191815458880472",
      "borrowRate": "0.028095622937424",
      "utilization": "0.084286868820044813"
    },
    {
      "symbol": "USDC",
      "vaultSymbol": "ibUSDC",
      "vaultAddr": "0x800933D685E7Dc753758cEb77C8bd34aBF1E26d7",
      "interestModelAddr": "0xADcfBf2e8470493060FbE0A0aFAC66d2cB028e9c",
      "decimals": 18,
      "supply": "4104550.33839455186550769",
      "debt": "1115337.371475089752471025",
      "supplyRate": "0.019936324788322253",
      "borrowRate": "0.090577308878928",
      "utilization": "0.271731926647863031"
    }
  ]
}