{
  "block": 12373330,
  "blockTime": "2021-11-05T00:00:01.000Z",
  "rates": [
    {
      "symbol": "WBNB",
      "vaultSymbol": "ibWBNB",
      "vaultAddr": "0xd7D069493685A581d27824Fc46EdA46B7EfC0063",
      "interestModelAddr": "0xADcfBf2e8470493060FbE0A0aFAC66d2cB028e9c",
      "decimals": 18,
      "supply": "558078.620656198072926011",
      "debt": "293289.283729230294563158",
      "supplyRate": "0.074570212882502619",
      "borrowRate": "0.175177996337664",
      "utilization": "0.525533989071962483"
    },
    {
      "symbol": "BUSD",
      "vaultSymbol": "ibBUSD",
      "vaultAddr": "0x7C9e73d4C71dae564d41F78d56439bB4ba87592f",
      "interestModelAddr": "0xADcfBf2e8470493060FbE0A0aFAC66d2cB028e9c",
      "decimals": 18,
      "supply": "172631107.445418592408630631",
      "debt": "121614438.23853085270160864",
      "supplyRate": "0.114125080258389345",
      "borrowRate": "0.199999999976256",
      "utilization": "0.704475804147767132"
    },
    {
      "symbol": "ETH",
      "vaultSymbol": "ibETH",
      "vaultAddr": "0xbfF4a34A4644a113E8200D7F1D79b3555f723AfE",
      "interestModelAddr": "0xADcfBf2e8470493060FbE0A0aFAC66d2cB028e9c",
      "decimals": 18,
      "supply": "53611.615124724015762021",
      "debt": "8052.137210380556612047",
      "supplyRate": "0.006090715518548408",
      "borrowRate": "0.050064631133904",
      "utilization": "0.150193893462224017"
    },
    {
      "symbol": "ALPACA",
      "vaultSymbol": "ibALPACA",
      "vaultAddr": "0xf1bE8ecC990cBcb90e166b71E368299f0116d421",
      "interestModelAddr": "0xADcfBf2e8470493060FbE0A0aFAC66d2cB028e9c",
      "decimals": 18,
      "supply": "93226870.674806869851392353",
      "debt": "2828972.339298675985050864",
      "supplyRate": "0.00024862165485254",
      "borrowRate": "0.01011501053568",
      "utilization": "0.03034503162898894"
    },
    {
      "symbol": "USDT",
      "vaultSymbol": "ibUSDT",
      "vaultAddr": "0x158Da805682BdC8ee32d52833aD41E74bb951E59",
      "interestModelAddr": "0xADcfBf2e8470493060FbE0A0aFAC66d2cB028e9c",
      "decimals": 18,
      "supply": "106068716.964011719326913381",
      "debt": "72827347.87345102917574406",
      "supplyRate": "0.111230065676210483",
      "borrowRate": "0.199999999976256",
      "utilization": "0.686605343761825411"
    },
    {
      "symbol": "BTCB",
      "vaultSymbol": "ibBTCB",
      "vaultAddr": "0x08FC9Ba2cAc74742177e0afC3dC8Aed6961c24e7",
      "interestModelAddr": "0xADcfBf2e8470493060FbE0A0aFAC66d2cB028e9c",
      "decimals": 18,
      "supply": "3219.581616651288216583",
      "debt": "249.981175880022394226",
      "supplyRate": "0.001627719248469366",
      "borrowRate": "0.025881331338288",
      "utilization": "0.077643994047906681"
    },
    {
      "symbol": "TUSD",
      "vaultSymbol": "ibTUSD",
      "vaultAddr": "0x3282d2a151ca00BfE7ed17Aa16E42880248CD3Cd",
      "interestModelAddr": "0xADcfBf2e8470493060FbE0A0aFAC66d2cB028e9c",
      "decimals": 18,
      "supply": "59541257.74062435852492594",
      "debt": "10964997.314231834650181398",
      "supplyRate": "0.009156822897236465",
      "borrowRate": "0.061385990863536",
      "utilization": "0.184157972644748737"
    }
  ]
}