{
  "block": 13474359,
  "blockTime": "2021-12-14T17:59:59.000Z",
  "rates": [
    {
      "symbol": "WBNB",
      "vaultSymbol": "ibWBNB",
      "vaultAddr": "0xd7D069493685A581d27824Fc46EdA46B7EfC0063",
      "interestModelAddr": "0xADcfBf2e8470493060FbE0A0aFAC66d2cB028e9c",
      "decimals": 18,
      "supply": "414327.165404680730135983",
      "debt": "192020.732943723754183309",
      "supplyRate": "0.05799268180432708",
      "borrowRate": "0.154483983480816",
      "utilization": "0.463451950480180753"
    },
    {
      "symbol": "BUSD",
      "vaultSymbol": "ibBUSD",
      "vaultAddr": "0x7C9e73d4C71dae564d41F78d56439bB4ba87592f",
      "interestModelAddr": "0xADcfBf2e8470493060FbE0A0aFAC66d2cB028e9c",
      "decimals": 18,
      "supply": "173053277.429356506445673542",
      "debt": "83957275.643987250638417248",
      "supplyRate": "0.06355076485743121",
      "borrowRate": "0.161717587571232",
      "utilization": "0.485152762727999397"
    },
    {
      "symbol": "ETH",
      "vaultSymbol": "ibETH",
      "vaultAddr": "0xbfF4a34A4644a113E8200D7F1D79b3555f723AfE",
      "interestModelAddr": "0xADcfBf2e8470493060FbE0A0aFAC66d2cB028e9c",
      "decimals": 18,
      "supply": "17295.691706371076325869",
      "debt": "2904.517884839060068195",
      "supplyRate": "0.007614405534787257",
      "borrowRate": "0.055977676072704",
      "utilization": "0.167933028302600116"
    },
    {
      "symbol": "ALPACA",
      "vaultSymbol": "ibALPACA",
      "vaultAddr": "0xf1bE8ecC990cBcb90e166b71E368299f0116d421",
      "interestModelAddr": "0xADcfBf2e8470493060FbE0A0aFAC66d2cB028e9c",
      "decimals": 18,
      "supply": "87557577.386171596271752518",
      "debt": "2657665.127073036533736157",
      "supplyRate": "0.000248757856307624",
      "borrowRate": "0.010117780784064",
      "utilization": "0.030353342410919363"
    },
    {
      "symbol": "USDT",
      "vaultSymbol": "ibUSDT",
      "vaultAddr": "0x158Da805682BdC8ee32d52833aD41E74bb951E59",
      "interestModelAddr": "0xADcfBf2e8470493060FbE0A0aFAC66d2cB028e9c",
      "decimals": 18,
      "supply": "138936527.316058363462719685",
      "debt": "53484411.048551700043310978",
      "supplyRate": "0.040011544920907405",
      "borrowRate": "0.128318573647008",
      "utilization": "0.384955721017002424"
    },
    {
      "symbol": "BTCB",
      "vaultSymbol": "ibBTCB",
      "vaultAddr": "0x08FC9Ba2cAc74742177e0afC3dC8Aed6961c24e7",
      "interestModelAddr": "0xADcfBf2e8470493060FbE0A0aFAC66d2cB028e9c",
      "decimals": 18,
      "supply": "1252.749425151521319579",
      "debt": "315.203310159359831351",
      "supplyRate": "0.017092944366842669",
      "borrowRate": "0.083869741162656",
      "utilization": "0.251609223545431417"
    },
    {
      "symbol": "TUSD",
      "vaultSymbol": "ibTUSD",
      "vaultAddr": "0x3282d2a151ca00BfE7ed17Aa16E42880248CD3Cd",
      "interestModelAddr": "0xADcfBf2e8470493060FbE0A0aFAC66d2cB028e9c",
      "decimals": 18,
      "supply": "59179806.682214344561960896",
      "debt": "6332184.764696945195549465",
      "supplyRate": "0.003091176738356931",
      "borrowRate": "0.035666359387632",
      "utilization": "0.10699907822781033"
    }
  ]
}