{
  "block": 13176197,
  "blockTime": "2021-12-04T02:59:59.000Z",
  "rates": [
    {
      "symbol": "WBNB",
      "vaultSymbol": "ibWBNB",
      "vaultAddr": "0xd7D069493685A581d27824Fc46EdA46B7EfC0063",
      "interestModelAddr": "0xADcfBf2e8470493060FbE0A0aFAC66d2cB028e9c",
      "decimals": 18,
      "supply": "356736.927284699480875101",
      "debt": "195461.24166724105337412",
      "supplyRate": "0.081056703276057304",
      "borrowRate": "0.182638079302608",
      "utilization": "0.547914237965194318"
    },
    {
      "symbol": "BUSD",
      "vaultSymbol": "ibBUSD",
      "vaultAddr": "0x7C9e73d4C71dae564d41F78d56439bB4ba87592f",
      "interestModelAddr": "0xADcfBf2e8470493060FbE0A0aFAC66d2cB028e9c",
      "decimals": 18,
      "supply": "165942914.496866521072799635",
      "debt": "97576496.36088570767372746",
      "supplyRate": "0.093354826737173653",
      "borrowRate": "0.19600414323696",
      "utilization": "0.588012429796924123"
    },
    {
      "symbol": "ETH",
      "vaultSymbol": "ibETH",
      "vaultAddr": "0xbfF4a34A4644a113E8200D7F1D79b3555f723AfE",
      "interestModelAddr": "0xADcfBf2e8470493060FbE0A0aFAC66d2cB028e9c",
      "decimals": 18,
      "supply": "22484.750446184076176226",
      "debt": "5072.641441864444571922",
      "supplyRate": "0.013742190082321599",
      "borrowRate": "0.075201211796688",
      "utilization": "0.225603635406384101"
    },
    {
      "symbol": "ALPACA",
      "vaultSymbol": "ibALPACA",
      "vaultAddr": "0xf1bE8ecC990cBcb90e166b71E368299f0116d421",
      "interestModelAddr": "0xADcfBf2e8470493060FbE0A0aFAC66d2cB028e9c",
      "decimals": 18,
      "supply": "90143799.681675346717068896",
      "debt": "2628781.597681063898864968",
      "supplyRate": "0.00022961542284081",
      "borrowRate": "0.009720696659184",
      "utilization": "0.02916208998249548"
    },
    {
      "symbol": "USDT",
      "vaultSymbol": "ibUSDT",
      "vaultAddr": "0x158Da805682BdC8ee32d52833aD41E74bb951E59",
      "interestModelAddr": "0xADcfBf2e8470493060FbE0A0aFAC66d2cB028e9c",
      "decimals": 18,
      "supply": "122325186.07905615212710886",
      "debt": "66012456.663616397640396354",
      "supplyRate": "0.078629186917187096",
      "borrowRate": "0.179882434073376",
      "utilization": "0.539647302240390285"
    },
    {
      "symbol": "BTCB",
      "vaultSymbol": "ibBTCB",
      "vaultAddr": "0x08FC9Ba2cAc74742177e0afC3dC8Aed6961c24e7",
      "interestModelAddr": "0xADcfBf2e8470493060FbE0A0aFAC66d2cB028e9c",
      "decimals": 18,
      "supply": "2087.822546034028885978",
      "debt": "346.082639915314195009",
      "supplyRate": "0.007418843805612457",
      "borrowRate": "0.055254159500544",
      "utilization": "0.165762478507918882"
    },
    {
      "symbol": "TUSD",
      "vaultSymbol": "ibTUSD",
      "vaultAddr": "0x3282d2a151ca00BfE7ed17Aa16E42880248CD3Cd",
      "interestModelAddr": "0xADcfBf2e8470493060FbE0A0aFAC66d2cB028e9c",
      "decimals": 18,
      "supply": "59261066.401823227229899229",
      "debt": "9086732.259044660911170701",
      "supplyRate": "0.006348049474977675",
      "borrowRate": "0.051111310280112",
      "utilization": "0.153333930871772133"
    }
  ]
}