{
  "blockNo": 11120209,
  "lpName": "USDT-WBNB LP",
  "lpTokens": 0,
  "token0_symbol": "USDT",
  "token0_decimals": 18,
  "token0": 0,
  "token0_liquidity": 128516417.28328465,
  "token0_price": 0.99985769,
  "token0_posVal": 43700976.007607415,
  "token0_posValUSD": 43694756.92171177,
  "token0_debtVal": 27649711.44343151,
  "token0_debtValUSD": 27645776.612995997,
  "token1_symbol": "WBNB",
  "token1_decimals": 18,
  "token1": 0,
  "token1_liquidity": 371667.45204153436,
  "token1_price": 347.0663663,
  "token1_posVal": 165062.56266585444,
  "token1_posValUSD": 57287663.83660414,
  "token1_debtVal": 97264.15584708912,
  "token1_debtValUSD": 33757117.141086124,
  "liquidity": 257491400.16397592,
  "tvl": 0,
  "health": 100982420.75831592,
  "debt": 61402893.75408212,
  "leverage": 2.551380180655365,
  "workerPositions": [
    {
      "name": "USDT-WBNB PancakeswapWorker",
      "address": "0x41867cc58aece8B570FF1A2a8aa6149014D2a94C",
      "vault": "ibWBNB",
      "borrowToken": "WBNB",
      "posVal": 165062.56266585444,
      "posValUSD": 57287663.83660414,
      "debtVal": 97264.15584708912,
      "debtValUSD": 33757117.141086124
    },
    {
      "name": "WBNB-USDT PancakeswapWorker",
      "address": "0x81b6534f4F7ba45Ecf98295Cef1450B4a4FC81Cd",
      "vault": "ibUSDT",
      "borrowToken": "USDT",
      "posVal": 43700976.007607415,
      "posValUSD": 43694756.92171177,
      "debtVal": 27649711.44343151,
      "debtValUSD": 27645776.612995997
    }
  ]
}