{
  "blockNo": 14524608,
  "lpName": "USDT-WBNB LP",
  "lpTokens": 0,
  "token0_symbol": "USDT",
  "token0_decimals": 18,
  "token0": 0,
  "token0_liquidity": 83933601.9594849,
  "token0_price": 1.00026784,
  "token0_posVal": 29137401.735103313,
  "token0_posValUSD": 29145205.896784045,
  "token0_debtVal": 17697685.673262164,
  "token0_debtValUSD": 17702425.82139289,
  "token1_symbol": "WBNB",
  "token1_decimals": 18,
  "token1": 0,
  "token1_liquidity": 175864.4846031322,
  "token1_price": 477.92591278,
  "token1_posVal": 101789.31729929766,
  "token1_posValUSD": 48647752.38151988,
  "token1_debtVal": 66263.10539354096,
  "token1_debtValUSD": 31668855.1288454,
  "liquidity": 168006277.06496996,
  "tvl": 0,
  "health": 77792958.27830392,
  "debt": 49371280.95023829,
  "leverage": 2.7370994815103855,
  "workerPositions": [
    {
      "name": "USDT-WBNB PancakeswapWorker",
      "address": "0x41867cc58aece8B570FF1A2a8aa6149014D2a94C",
      "vault": "ibWBNB",
      "borrowToken": "WBNB",
      "posVal": 101789.31729929766,
      "posValUSD": 48647752.38151988,
      "debtVal": 66263.10539354096,
      "debtValUSD": 31668855.1288454
    },
    {
      "name": "WBNB-USDT PancakeswapWorker",
      "address": "0x81b6534f4F7ba45Ecf98295Cef1450B4a4FC81Cd",
      "vault": "ibUSDT",
      "borrowToken": "USDT",
      "posVal": 29137401.735103313,
      "posValUSD": 29145205.896784045,
      "debtVal": 17697685.673262164,
      "debtValUSD": 17702425.82139289
    }
  ]
}