{
  "blockNo": 16978667,
  "lpName": "USDT-WBNB LP",
  "lpTokens": 0,
  "token0_symbol": "USDT",
  "token0_decimals": 18,
  "token0": 0,
  "token0_liquidity": 168060573.8917149,
  "token0_price": 1.00010068,
  "token0_posVal": 53258248.61393505,
  "token0_posValUSD": 53263610.65440551,
  "token0_debtVal": 26927219.893303085,
  "token0_debtValUSD": 26929930.925801944,
  "token1_symbol": "WBNB",
  "token1_decimals": 18,
  "token1": 0,
  "token1_liquidity": 403384.18259705434,
  "token1_price": 417.38959632,
  "token1_posVal": 174107.5956330821,
  "token1_posValUSD": 72670699.05753793,
  "token1_debtVal": 110022.87660706247,
  "token1_debtValUSD": 45922404.05298698,
  "liquidity": 336445855.36635196,
  "tvl": 0,
  "health": 125934309.71194345,
  "debt": 72852334.97878893,
  "leverage": 2.372449599793921,
  "workerPositions": [
    {
      "name": "USDT-WBNB PancakeswapWorker",
      "address": "0x41867cc58aece8B570FF1A2a8aa6149014D2a94C",
      "vault": "ibWBNB",
      "borrowToken": "WBNB",
      "posVal": 174107.5956330821,
      "posValUSD": 72670699.05753793,
      "debtVal": 110022.87660706247,
      "debtValUSD": 45922404.05298698
    },
    {
      "name": "WBNB-USDT PancakeswapWorker",
      "address": "0x81b6534f4F7ba45Ecf98295Cef1450B4a4FC81Cd",
      "vault": "ibUSDT",
      "borrowToken": "USDT",
      "posVal": 53258248.61393505,
      "posValUSD": 53263610.65440551,
      "debtVal": 26927219.893303085,
      "debtValUSD": 26929930.925801944
    }
  ]
}