{
  "blockNo": 12450594,
  "lpName": "USDT-WBNB LP",
  "lpTokens": 0,
  "token0_symbol": "USDT",
  "token0_decimals": 18,
  "token0": 0,
  "token0_liquidity": 149540339.70714933,
  "token0_price": 1.00085723,
  "token0_posVal": 54771881.26323342,
  "token0_posValUSD": 54818833.36300871,
  "token0_debtVal": 31406084.376896143,
  "token0_debtValUSD": 31433006.61460655,
  "token1_symbol": "WBNB",
  "token1_decimals": 18,
  "token1": 0,
  "token1_liquidity": 226391.76003975267,
  "token1_price": 662.29970051,
  "token1_posVal": 127128.34356260474,
  "token1_posValUSD": 84197063.8678455,
  "token1_debtVal": 91250.14131880051,
  "token1_debtValUSD": 60434941.26693675,
  "liquidity": 299607725.0448165,
  "tvl": 0,
  "health": 139015897.2308542,
  "debt": 91867947.88154331,
  "leverage": 2.948503575434634,
  "workerPositions": [
    {
      "name": "USDT-WBNB PancakeswapWorker",
      "address": "0x41867cc58aece8B570FF1A2a8aa6149014D2a94C",
      "vault": "ibWBNB",
      "borrowToken": "WBNB",
      "posVal": 127128.34356260474,
      "posValUSD": 84197063.8678455,
      "debtVal": 91250.14131880051,
      "debtValUSD": 60434941.26693675
    },
    {
      "name": "WBNB-USDT PancakeswapWorker",
      "address": "0x81b6534f4F7ba45Ecf98295Cef1450B4a4FC81Cd",
      "vault": "ibUSDT",
      "borrowToken": "USDT",
      "posVal": 54771881.26323342,
      "posValUSD": 54818833.36300871,
      "debtVal": 31406084.376896143,
      "debtValUSD": 31433006.61460655
    }
  ]
}