{
  "blockNo": 13357274,
  "lpName": "USDT-WBNB LP",
  "lpTokens": 0,
  "token0_symbol": "USDT",
  "token0_decimals": 18,
  "token0": 0,
  "token0_liquidity": 131359542.14625461,
  "token0_price": 1.00049066,
  "token0_posVal": 47119837.92263477,
  "token0_posValUSD": 47142957.7423099,
  "token0_debtVal": 29113571.262587167,
  "token0_debtValUSD": 29127856.12746287,
  "token1_symbol": "WBNB",
  "token1_decimals": 18,
  "token1": 0,
  "token1_liquidity": 231053.05737511697,
  "token1_price": 570.08,
  "token1_posVal": 143575.36024133206,
  "token1_posValUSD": 81849441.36637859,
  "token1_debtVal": 94100.44651828274,
  "token1_debtValUSD": 53644782.551142626,
  "liquidity": 263142721.9676108,
  "tvl": 0,
  "health": 128992399.10868849,
  "debt": 82772638.6786055,
  "leverage": 2.79084958269778,
  "workerPositions": [
    {
      "name": "USDT-WBNB PancakeswapWorker",
      "address": "0x41867cc58aece8B570FF1A2a8aa6149014D2a94C",
      "vault": "ibWBNB",
      "borrowToken": "WBNB",
      "posVal": 143575.36024133206,
      "posValUSD": 81849441.36637859,
      "debtVal": 94100.44651828274,
      "debtValUSD": 53644782.551142626
    },
    {
      "name": "WBNB-USDT PancakeswapWorker",
      "address": "0x81b6534f4F7ba45Ecf98295Cef1450B4a4FC81Cd",
      "vault": "ibUSDT",
      "borrowToken": "USDT",
      "posVal": 47119837.92263477,
      "posValUSD": 47142957.7423099,
      "debtVal": 29113571.262587167,
      "debtValUSD": 29127856.12746287
    }
  ]
}