{
  "blockNo": 11208494,
  "lpName": "USDT-WBNB LP",
  "lpTokens": 0,
  "token0_symbol": "USDT",
  "token0_decimals": 18,
  "token0": 0,
  "token0_liquidity": 129613385.89652182,
  "token0_price": 1.00151335,
  "token0_posVal": 45847515.98220285,
  "token0_posValUSD": 45916899.320514515,
  "token0_debtVal": 28083932.166033104,
  "token0_debtValUSD": 28126432.984776568,
  "token1_symbol": "WBNB",
  "token1_decimals": 18,
  "token1": 0,
  "token1_liquidity": 363132.5479076271,
  "token1_price": 358.05,
  "token1_posVal": 164777.37182455204,
  "token1_posValUSD": 58998537.981780864,
  "token1_debtVal": 98694.57978112536,
  "token1_debtValUSD": 35337594.290631935,
  "liquidity": 259829145.09239417,
  "tvl": 0,
  "health": 104915437.30229539,
  "debt": 63464027.27540851,
  "leverage": 2.5310462836907948,
  "workerPositions": [
    {
      "name": "USDT-WBNB PancakeswapWorker",
      "address": "0x41867cc58aece8B570FF1A2a8aa6149014D2a94C",
      "vault": "ibWBNB",
      "borrowToken": "WBNB",
      "posVal": 164777.37182455204,
      "posValUSD": 58998537.981780864,
      "debtVal": 98694.57978112536,
      "debtValUSD": 35337594.290631935
    },
    {
      "name": "WBNB-USDT PancakeswapWorker",
      "address": "0x81b6534f4F7ba45Ecf98295Cef1450B4a4FC81Cd",
      "vault": "ibUSDT",
      "borrowToken": "USDT",
      "posVal": 45847515.98220285,
      "posValUSD": 45916899.320514515,
      "debtVal": 28083932.166033104,
      "debtValUSD": 28126432.984776568
    }
  ]
}