{
  "block": 31517924,
  "blockTime": "2022-02-20T13:00:00.000Z",
  "rates": [
    {
      "symbol": "WFTM",
      "vaultSymbol": "ibFTM",
      "vaultAddr": "0xc1018f4Bba361A1Cc60407835e156595e92EF7Ad",
      "interestModelAddr": "0xADaBC5FC5da42c85A84e66096460C769a151A8F8",
      "decimals": 18,
      "supply": "10444947.509398602377660893",
      "debt": "4755674.209543056585817462",
      "supplyRate": "0.055972593591141607",
      "borrowRate": "0.15176952634896",
      "utilization": "0.455308579125341921"
    },
    {
      "symbol": "USDC",
      "vaultSymbol": "ibUSDC",
      "vaultAddr": "0x831332f94C4A0092040b28ECe9377AfEfF34B25a",
      "interestModelAddr": "0xADaBC5FC5da42c85A84e66096460C769a151A8F8",
      "decimals": 6,
      "supply": "5039070.896141",
      "debt": "1972842.250501",
      "supplyRate": "0.04138543718940989",
      "borrowRate": "0.130503042533952",
      "utilization": "0.391509127607598004"
    },
    {
      "symbol": "ALPACA",
      "vaultSymbol": "ibALPACA",
      "vaultAddr": "0x2E7f32e38EA5a5fcb4494d9B626d2d393B176B1E",
      "interestModelAddr": "0xADaBC5FC5da42c85A84e66096460C769a151A8F8",
      "decimals": 18,
      "supply": "1070405.441738400269670252",
      "debt": "532294.324997838825102635",
      "supplyRate": "0.0667683769988672",
      "borrowRate": "0.165760967517264",
      "utilization": "0.497282902573217577"
    }
  ]
}